CHANGES.txt
LICENSE.txt
MANIFEST.in
README.md
setup.py
memsql/__init__.py
memsql.egg-info/PKG-INFO
memsql.egg-info/SOURCES.txt
memsql.egg-info/dependency_links.txt
memsql.egg-info/not-zip-safe
memsql.egg-info/requires.txt
memsql.egg-info/top_level.txt
memsql/common/__init__.py
memsql/common/connection_pool.py
memsql/common/conversions.py
memsql/common/database.py
memsql/common/errorcodes.py
memsql/common/exceptions.py
memsql/common/json.py
memsql/common/query_builder.py
memsql/common/random_aggregator_pool.py
memsql/common/util.py