Metadata-Version: 2.1
Name: memsql
Version: 3.2.0
Summary: Useful utilities and plugins for MemSQL integration.
Home-page: http://github.com/memsql/memsql-python
Author: MemSQL
Author-email: support@memsql.com
License: LICENSE.txt
Platform: UNKNOWN
Classifier: License :: OSI Approved :: MIT License
Classifier: Programming Language :: Python :: 3.4
Classifier: Programming Language :: Python :: 3.5
Classifier: Programming Language :: Python :: 3.6
Classifier: Programming Language :: Python :: 3.7
License-File: LICENSE.txt
